GenMine/.gitignore
GenMine/__init__.py
GenMine/main.py
GenMine/meta.yaml
GenMine/src/__init__.py
GenMine/src/command.py
GenMine/src/genmine_module.py
GenMine/src/logger.py
genmine-1.4.0.dist-info/METADATA
genmine-1.4.0.dist-info/WHEEL
genmine-1.4.0.dist-info/entry_points.txt
genmine-1.4.0.dist-info/licenses/LICENSE
genmine-1.4.0.dist-info/RECORD
