Metadata-Version: 2.4
Name: genmine
Version: 1.4.0
Summary: GenBank data miner for fungal taxonomists
Project-URL: Homepage, https://github.com/Changwanseo/GenMine
Author-email: Changwan Seo <wan101010@snu.ac.kr>
License-Expression: GPL-3.0
License-File: LICENSE
Classifier: Operating System :: OS Independent
Classifier: Programming Language :: Python :: 3
Requires-Python: >=3.8
Requires-Dist: biopython
Requires-Dist: numpy
Requires-Dist: openpyxl
Requires-Dist: pandas
Requires-Dist: python-dateutil
Requires-Dist: pytz
Requires-Dist: xlrd
Requires-Dist: xmltodict
